Metadata-Version: 2.1
Name: pybenzinaparse
Version: 0.2.2
Summary: MP4 / ISO base media file format (ISO/IEC 14496-12 - MPEG-4 Part 12) file parser
Home-page: https://github.com/satyaog/pybenzinaparse
Author: Satya Ortiz-Gagné
Author-email: satya.ortiz-gagne@mila.quebec
License: The MIT License
Requires: bitstring
License-File: LICENSE
